zh_segment.py
zh_segment-1.2.1.dist-info/DESCRIPTION.rst
zh_segment-1.2.1.dist-info/METADATA
zh_segment-1.2.1.dist-info/RECORD
zh_segment-1.2.1.dist-info/WHEEL
zh_segment-1.2.1.dist-info/metadata.json
zh_segment-1.2.1.dist-info/top_level.txt
zh_segment_data/__init__.py
zh_segment_data/bigrams.txt
zh_segment_data/unigrams.txt
